snitun/__init__.py
snitun/exceptions.py
snitun/client/__init__.py
snitun/client/client_peer.py
snitun/client/connector.py
snitun/metrics/__init__.py
snitun/metrics/base.py
snitun/metrics/factory.py
snitun/metrics/noop.py
snitun/multiplexer/__init__.py
snitun/multiplexer/channel.py
snitun/multiplexer/const.py
snitun/multiplexer/core.py
snitun/multiplexer/crypto.py
snitun/multiplexer/message.py
snitun/multiplexer/queue.py
snitun/server/__init__.py
snitun/server/listener_peer.py
snitun/server/listener_sni.py
snitun/server/peer.py
snitun/server/peer_manager.py
snitun/server/run.py
snitun/server/sni.py
snitun/server/worker.py
snitun/utils/__init__.py
snitun/utils/aes.py
snitun/utils/aiohttp_client.py
snitun/utils/asyncio.py
snitun/utils/ipaddress.py
snitun/utils/server.py
snitun-0.45.1.dist-info/licenses/LICENSE
snitun-0.45.1.dist-info/METADATA
snitun-0.45.1.dist-info/WHEEL
snitun-0.45.1.dist-info/top_level.txt
snitun-0.45.1.dist-info/RECORD
