Metadata-Version: 2.4
Name: snitun
Version: 0.45.1
Summary: SNI proxy with TCP multiplexer
Author-email: "Nabu Casa, Inc." <opensource@nabucasa.com>
License: GPL v3
Project-URL: Homepage, https://www.nabucasa.com/
Project-URL: Repository, https://github.com/NabuCasa/snitun.git
Keywords: sni,proxy,multiplexer,tls
Platform: any
Classifier: Intended Audience :: End Users/Desktop
Classifier: Intended Audience :: Developers
Classifier: License :: OSI Approved :: GNU General Public License v3 (GPLv3)
Classifier: Operating System :: OS Independent
Classifier: Topic :: Internet :: Proxy Servers
Classifier: Topic :: Software Development :: Libraries :: Python Modules
Classifier: Development Status :: 5 - Production/Stable
Classifier: Programming Language :: Python :: 3.12
Classifier: Programming Language :: Python :: 3.13
Requires-Python: >=3.12
License-File: LICENSE
Requires-Dist: aiohttp>=3.9.3
Requires-Dist: cryptography>=2.5
Provides-Extra: lint
Requires-Dist: ruff==0.12.11; extra == "lint"
Provides-Extra: test
Requires-Dist: covdefaults==2.3.0; extra == "test"
Requires-Dist: pytest-aiohttp==1.1.0; extra == "test"
Requires-Dist: pytest-codspeed==4.0.0; extra == "test"
Requires-Dist: pytest-cov==6.2.1; extra == "test"
Requires-Dist: pytest-timeout==2.4.0; extra == "test"
Requires-Dist: pytest==8.4.1; extra == "test"
Dynamic: license-file
